fooddata/__init__.py
fooddata/cli.py
fooddata/db.py
fooddata/download.py
fooddata-0.1.1.dist-info/entry_points.txt
fooddata-0.1.1.dist-info/LICENSE.md
fooddata-0.1.1.dist-info/WHEEL
fooddata-0.1.1.dist-info/METADATA
fooddata-0.1.1.dist-info/RECORD
