Metadata-Version: 2.1
Name: fooddata
Version: 0.1.1
Summary: Download, build, and query the USDA food database
Home-page: https://github.com/mfdeux/fooddata
License: MIT
Author: Marc Ford
Author-email: mrfxyz567@gmail.com
Requires-Python: >=3.8,<4.0
Classifier: License :: OSI Approved :: MIT License
Classifier: Programming Language :: Python :: 3
Classifier: Programming Language :: Python :: 3.8
Requires-Dist: click (>=7.1.2,<8.0.0)
Requires-Dist: requests (>=2.24.0,<3.0.0)
Requires-Dist: tqdm (>=4.48.2,<5.0.0)
Project-URL: Repository, https://github.com/mfdeux/fooddata
